recipe2org/__init__.py
recipe2org/__main__.py
recipe2org/main.py
recipe2org-0.0.4.dist-info/METADATA
recipe2org-0.0.4.dist-info/WHEEL
recipe2org-0.0.4.dist-info/entry_points.txt
recipe2org-0.0.4.dist-info/licenses/LICENSE
recipe2org-0.0.4.dist-info/RECORD
